CHANGES.rst
MANIFEST.in
README.rst
TODO.txt
setup.cfg
setup.py
docs/INSTALL.txt
docs/LICENSE.GPL
docs/LICENSE.txt
poi/__init__.py
poi.receivemail.egg-info/PKG-INFO
poi.receivemail.egg-info/SOURCES.txt
poi.receivemail.egg-info/dependency_links.txt
poi.receivemail.egg-info/entry_points.txt
poi.receivemail.egg-info/namespace_packages.txt
poi.receivemail.egg-info/not-zip-safe
poi.receivemail.egg-info/requires.txt
poi.receivemail.egg-info/top_level.txt
poi/receivemail/__init__.py
poi/receivemail/config.py
poi/receivemail/configure.zcml
poi/receivemail/poimail.py