Metadata-Version: 1.1
Name: poi.receivemail
Version: 1.13
Summary: Receive email in the Poi issue tracker
Home-page: https://github.com/collective/poi.receivemail
Author: Maurits van Rees
Author-email: maurits@vanrees.org
License: GPL
Keywords: poi issue tracker mail
Platform: UNKNOWN
Classifier: Framework :: Plone
Classifier: Framework :: Plone :: 3.2
Classifier: Framework :: Plone :: 3.3
Classifier: Framework :: Plone :: 4.0
Classifier: Framework :: Plone :: 4.1
Classifier: Framework :: Plone :: 4.2
Classifier: Framework :: Plone :: 4.3
Classifier: Programming Language :: Python
Classifier: Programming Language :: Python :: 2.4
Classifier: Programming Language :: Python :: 2.6
Classifier: Programming Language :: Python :: 2.7
